embedeval/__init__.py
embedeval/__main__.py
embedeval/cli.py
embedeval/embedding.py
embedeval/errors.py
embedeval/logger.py
embedeval/task.py
embedeval/taskregistry.py
embedeval/taskreport.py
embedeval/parsers/__init__.py
embedeval/parsers/word2vec_gensim.py
embedeval/parsers/word2vec_simple.py
embedeval/tasks/__init__.py
embedeval/tasks/de_offense_detection.py
embedeval/tasks/en_got_odd_one_out.py
embedeval/tasks/en_got_word_analogy.py
embedeval/tasks/skeleton.py.in
embedeval/tasks/data/germeval-2018/test.txt
embedeval/tasks/data/germeval-2018/train.txt
embedeval-1.0.4.dist-info/LICENSE
embedeval-1.0.4.dist-info/METADATA
embedeval-1.0.4.dist-info/WHEEL
embedeval-1.0.4.dist-info/entry_points.txt
embedeval-1.0.4.dist-info/top_level.txt
embedeval-1.0.4.dist-info/RECORD
