Metadata-Version: 2.1
Name: embedeval
Version: 1.0.4
Summary: NLP Embeddings Evaluation Tool
Home-page: https://github.com/timofurrer/hslu-wipro
Author: Timo Furrer, David Staub
Author-email: tuxtimo@gmail.com, david_staub@hotmail.com
Maintainer: Timo Furrer, David Staub
Maintainer-email: tuxtimo@gmail.com, david_staub@hotmail.com
License: MIT
Download-URL: https://github.com/timofurrer/hslu-wipro
Keywords: machine-learning,natural-language-processing,nlp,embeddings,evaluation,report
Platform: Linux
Platform: Windows
Platform: MAC OS X
Classifier: Development Status :: 5 - Production/Stable
Classifier: Environment :: Console
Classifier: Intended Audience :: Developers
Classifier: Intended Audience :: Education
Classifier: Intended Audience :: Other Audience
Classifier: License :: OSI Approved :: MIT License
Classifier: Natural Language :: English
Classifier: Operating System :: OS Independent
Classifier: Programming Language :: Python
Classifier: Programming Language :: Python :: 3.7
Classifier: Programming Language :: Python :: Implementation :: CPython
Classifier: Topic :: Education :: Testing
Requires-Python: >=3.7.*
Requires-Dist: click (>=7)
Requires-Dist: click-default-group
Requires-Dist: colorful
Requires-Dist: numpy
Requires-Dist: pandas
Requires-Dist: gensim
Requires-Dist: keras
Requires-Dist: tensorflow
Requires-Dist: nltk
Requires-Dist: python-dateutil (<2.8.1)
Provides-Extra: dev
Requires-Dist: coverage ; extra == 'dev'
Requires-Dist: pytest ; extra == 'dev'
Requires-Dist: pytest-mock ; extra == 'dev'
Requires-Dist: pytest-benchmark ; extra == 'dev'
Requires-Dist: sphinx ; extra == 'dev'
Requires-Dist: jupyter ; extra == 'dev'
Requires-Dist: matplotlib ; extra == 'dev'
Requires-Dist: seaborn ; extra == 'dev'
Requires-Dist: pre-commit ; extra == 'dev'
Provides-Extra: docs
Requires-Dist: sphinx ; extra == 'docs'
Provides-Extra: notebooks
Requires-Dist: jupyter ; extra == 'notebooks'
Requires-Dist: matplotlib ; extra == 'notebooks'
Requires-Dist: seaborn ; extra == 'notebooks'
Provides-Extra: tests
Requires-Dist: coverage ; extra == 'tests'
Requires-Dist: pytest ; extra == 'tests'
Requires-Dist: pytest-mock ; extra == 'tests'
Requires-Dist: pytest-benchmark ; extra == 'tests'
